{
	"credit": "Made with Blockbench",
	"textures": {
		"0": "frog-signals:block/redirector",
		"1": "frog-signals:block/redirector_arrow",
		"particle": "block/polished_tuff"
	},
	"elements": [
		{
			"from": [4, 4, 1],
			"to": [5, 12, 5],
			"rotation": {"angle": 0, "axis": "y", "origin": [8, 8, 8]},
			"faces": {
				"north": {"uv": [0, 4, 2, 4.25], "rotation": 90, "texture": "#0"},
				"east": {"uv": [0, 4, 2, 5], "rotation": 90, "texture": "#0"},
				"west": {"uv": [0, 4, 2, 5], "rotation": 90, "texture": "#0"},
				"up": {"uv": [0, 4, 1, 4.25], "rotation": 90, "texture": "#0"},
				"down": {"uv": [0, 4, 1, 4.25], "rotation": 90, "texture": "#0"}
			}
		},
		{
			"from": [11, 4, 1],
			"to": [12, 12, 5],
			"rotation": {"angle": 0, "axis": "y", "origin": [8, 8, 8]},
			"faces": {
				"north": {"uv": [0, 4, 2, 4.25], "rotation": 90, "texture": "#0"},
				"east": {"uv": [0, 4, 2, 5], "rotation": 90, "texture": "#0"},
				"west": {"uv": [0, 4, 2, 5], "rotation": 90, "texture": "#0"},
				"up": {"uv": [0, 4, 1, 4.25], "rotation": 90, "texture": "#0"},
				"down": {"uv": [0, 4, 1, 4.25], "rotation": 90, "texture": "#0"}
			}
		},
		{
			"from": [5, 4, 1],
			"to": [11, 5, 5],
			"rotation": {"angle": 0, "axis": "y", "origin": [8, 8, 8]},
			"faces": {
				"north": {"uv": [0, 4, 1.5, 4.25], "texture": "#0"},
				"east": {"uv": [0, 4, 1, 4.25], "texture": "#0"},
				"west": {"uv": [0, 4, 1, 4.25], "texture": "#0"},
				"up": {"uv": [0, 4, 1.5, 5], "texture": "#0"},
				"down": {"uv": [0, 4, 1.5, 5], "texture": "#0"}
			}
		},
		{
			"from": [5, 11, 1],
			"to": [11, 12, 5],
			"rotation": {"angle": 0, "axis": "y", "origin": [8, 8, 8]},
			"faces": {
				"north": {"uv": [0, 4, 1.5, 4.25], "texture": "#0"},
				"east": {"uv": [0, 4, 1, 4.25], "texture": "#0"},
				"west": {"uv": [0, 4, 1, 4.25], "texture": "#0"},
				"up": {"uv": [0, 4, 1.5, 5], "texture": "#0"},
				"down": {"uv": [0, 4, 1.5, 5], "texture": "#0"}
			}
		},
		{
			"from": [5, 5, 4],
			"to": [11, 11, 4],
			"rotation": {"angle": 0, "axis": "y", "origin": [8, 8, 8]},
			"faces": {
				"north": {"uv": [4, 0, 5.5, 1.5], "texture": "#0"},
				"east": {"uv": [0, 0, 0, 1.5], "texture": "#0"},
				"west": {"uv": [0, 0, 0, 1.5], "texture": "#0"},
				"up": {"uv": [0, 0, 1.5, 0], "texture": "#0"},
				"down": {"uv": [0, 0, 1.5, 0], "texture": "#0"}
			}
		},
		{
			"from": [1, 4, 11],
			"to": [5, 12, 12],
			"rotation": {"angle": 0, "axis": "y", "origin": [8, 8, 8]},
			"faces": {
				"north": {"uv": [0, 4, 2, 5], "rotation": 90, "texture": "#0"},
				"south": {"uv": [0, 4, 2, 5], "rotation": 90, "texture": "#0"},
				"west": {"uv": [0, 4, 2, 4.25], "rotation": 90, "texture": "#0"},
				"up": {"uv": [0, 4, 1, 4.25], "texture": "#0"},
				"down": {"uv": [0, 4, 1, 4.25], "rotation": 180, "texture": "#0"}
			}
		},
		{
			"from": [1, 4, 4],
			"to": [5, 12, 5],
			"rotation": {"angle": 0, "axis": "y", "origin": [8, 8, 8]},
			"faces": {
				"north": {"uv": [0, 4, 2, 5], "rotation": 90, "texture": "#0"},
				"south": {"uv": [0, 4, 2, 5], "rotation": 90, "texture": "#0"},
				"west": {"uv": [0, 4, 2, 4.25], "rotation": 90, "texture": "#0"},
				"up": {"uv": [0, 4, 1, 4.25], "texture": "#0"},
				"down": {"uv": [0, 4, 1, 4.25], "rotation": 180, "texture": "#0"}
			}
		},
		{
			"from": [1, 4, 5],
			"to": [5, 5, 11],
			"rotation": {"angle": 0, "axis": "y", "origin": [8, 8, 8]},
			"faces": {
				"north": {"uv": [0, 4, 1, 4.25], "texture": "#0"},
				"south": {"uv": [0, 4, 1, 4.25], "texture": "#0"},
				"west": {"uv": [0, 4, 1.5, 4.25], "texture": "#0"},
				"up": {"uv": [0, 4, 1.5, 5], "rotation": 270, "texture": "#0"},
				"down": {"uv": [0, 4, 1.5, 5], "rotation": 90, "texture": "#0"}
			}
		},
		{
			"from": [1, 11, 5],
			"to": [5, 12, 11],
			"rotation": {"angle": 0, "axis": "y", "origin": [8, 8, 8]},
			"faces": {
				"north": {"uv": [0, 4, 1, 4.25], "texture": "#0"},
				"south": {"uv": [0, 4, 1, 4.25], "texture": "#0"},
				"west": {"uv": [0, 4, 1.5, 4.25], "texture": "#0"},
				"up": {"uv": [0, 4, 1.5, 5], "rotation": 270, "texture": "#0"},
				"down": {"uv": [0, 4, 1.5, 5], "rotation": 90, "texture": "#0"}
			}
		},
		{
			"from": [4, 5, 5],
			"to": [4, 11, 11],
			"rotation": {"angle": 0, "axis": "y", "origin": [8, 8, 8]},
			"faces": {
				"north": {"uv": [0, 0, 0, 1.5], "texture": "#0"},
				"south": {"uv": [0, 0, 0, 1.5], "texture": "#0"},
				"west": {"uv": [4, 0, 5.5, 1.5], "texture": "#0"},
				"up": {"uv": [0, 0, 1.5, 0], "rotation": 270, "texture": "#0"},
				"down": {"uv": [0, 0, 1.5, 0], "rotation": 90, "texture": "#0"}
			}
		},
		{
			"from": [11, 4, 11],
			"to": [12, 12, 15],
			"rotation": {"angle": 0, "axis": "y", "origin": [8, 8, 8]},
			"faces": {
				"east": {"uv": [0, 4, 2, 5], "rotation": 90, "texture": "#0"},
				"south": {"uv": [0, 4, 2, 4.25], "rotation": 90, "texture": "#0"},
				"west": {"uv": [0, 4, 2, 5], "rotation": 90, "texture": "#0"},
				"up": {"uv": [0, 4, 1, 4.25], "rotation": 270, "texture": "#0"},
				"down": {"uv": [0, 4, 1, 4.25], "rotation": 270, "texture": "#0"}
			}
		},
		{
			"from": [4, 4, 11],
			"to": [5, 12, 15],
			"rotation": {"angle": 0, "axis": "y", "origin": [8, 8, 8]},
			"faces": {
				"east": {"uv": [0, 4, 2, 5], "rotation": 90, "texture": "#0"},
				"south": {"uv": [0, 4, 2, 4.25], "rotation": 90, "texture": "#0"},
				"west": {"uv": [0, 4, 2, 5], "rotation": 90, "texture": "#0"},
				"up": {"uv": [0, 4, 1, 4.25], "rotation": 270, "texture": "#0"},
				"down": {"uv": [0, 4, 1, 4.25], "rotation": 270, "texture": "#0"}
			}
		},
		{
			"from": [5, 4, 11],
			"to": [11, 5, 15],
			"rotation": {"angle": 0, "axis": "y", "origin": [8, 8, 8]},
			"faces": {
				"east": {"uv": [0, 4, 1, 4.25], "texture": "#0"},
				"south": {"uv": [0, 4, 1.5, 4.25], "texture": "#0"},
				"west": {"uv": [0, 4, 1, 4.25], "texture": "#0"},
				"up": {"uv": [0, 4, 1.5, 5], "rotation": 180, "texture": "#0"},
				"down": {"uv": [0, 4, 1.5, 5], "rotation": 180, "texture": "#0"}
			}
		},
		{
			"from": [5, 11, 11],
			"to": [11, 12, 15],
			"rotation": {"angle": 0, "axis": "y", "origin": [8, 8, 8]},
			"faces": {
				"east": {"uv": [0, 4, 1, 4.25], "texture": "#0"},
				"south": {"uv": [0, 4, 1.5, 4.25], "texture": "#0"},
				"west": {"uv": [0, 4, 1, 4.25], "texture": "#0"},
				"up": {"uv": [0, 4, 1.5, 5], "rotation": 180, "texture": "#0"},
				"down": {"uv": [0, 4, 1.5, 5], "rotation": 180, "texture": "#0"}
			}
		},
		{
			"from": [5, 5, 12],
			"to": [11, 11, 12],
			"rotation": {"angle": 0, "axis": "y", "origin": [8, 8, 8]},
			"faces": {
				"east": {"uv": [0, 0, 0, 1.5], "texture": "#0"},
				"south": {"uv": [4, 0, 5.5, 1.5], "texture": "#0"},
				"west": {"uv": [0, 0, 0, 1.5], "texture": "#0"},
				"up": {"uv": [0, 0, 1.5, 0], "rotation": 180, "texture": "#0"},
				"down": {"uv": [0, 0, 1.5, 0], "rotation": 180, "texture": "#0"}
			}
		},
		{
			"from": [11, 4, 4],
			"to": [15, 12, 5],
			"rotation": {"angle": 0, "axis": "y", "origin": [8, 8, 8]},
			"faces": {
				"north": {"uv": [0, 4, 2, 5], "rotation": 90, "texture": "#0"},
				"east": {"uv": [0, 4, 2, 4.25], "rotation": 90, "texture": "#0"},
				"south": {"uv": [0, 4, 2, 5], "rotation": 90, "texture": "#0"},
				"up": {"uv": [0, 4, 1, 4.25], "rotation": 180, "texture": "#0"},
				"down": {"uv": [0, 4, 1, 4.25], "texture": "#0"}
			}
		},
		{
			"from": [11, 4, 11],
			"to": [15, 12, 12],
			"rotation": {"angle": 0, "axis": "y", "origin": [8, 8, 8]},
			"faces": {
				"north": {"uv": [0, 4, 2, 5], "rotation": 90, "texture": "#0"},
				"east": {"uv": [0, 4, 2, 4.25], "rotation": 90, "texture": "#0"},
				"south": {"uv": [0, 4, 2, 5], "rotation": 90, "texture": "#0"},
				"up": {"uv": [0, 4, 1, 4.25], "rotation": 180, "texture": "#0"},
				"down": {"uv": [0, 4, 1, 4.25], "texture": "#0"}
			}
		},
		{
			"from": [11, 4, 5],
			"to": [15, 5, 11],
			"rotation": {"angle": 0, "axis": "y", "origin": [8, 8, 8]},
			"faces": {
				"north": {"uv": [0, 4, 1, 4.25], "texture": "#0"},
				"east": {"uv": [0, 4, 1.5, 4.25], "texture": "#0"},
				"south": {"uv": [0, 4, 1, 4.25], "texture": "#0"},
				"up": {"uv": [0, 4, 1.5, 5], "rotation": 90, "texture": "#0"},
				"down": {"uv": [0, 4, 1.5, 5], "rotation": 270, "texture": "#0"}
			}
		},
		{
			"from": [11, 11, 5],
			"to": [15, 12, 11],
			"rotation": {"angle": 0, "axis": "y", "origin": [8, 8, 8]},
			"faces": {
				"north": {"uv": [0, 4, 1, 4.25], "texture": "#0"},
				"east": {"uv": [0, 4, 1.5, 4.25], "texture": "#0"},
				"south": {"uv": [0, 4, 1, 4.25], "texture": "#0"},
				"up": {"uv": [0, 4, 1.5, 5], "rotation": 90, "texture": "#0"},
				"down": {"uv": [0, 4, 1.5, 5], "rotation": 270, "texture": "#0"}
			}
		},
		{
			"from": [12, 5, 5],
			"to": [12, 11, 11],
			"rotation": {"angle": 0, "axis": "y", "origin": [8, 8, 8]},
			"faces": {
				"north": {"uv": [0, 0, 0, 1.5], "texture": "#0"},
				"east": {"uv": [4, 0, 5.5, 1.5], "texture": "#0"},
				"south": {"uv": [0, 0, 0, 1.5], "texture": "#0"},
				"up": {"uv": [0, 0, 1.5, 0], "rotation": 90, "texture": "#0"},
				"down": {"uv": [0, 0, 1.5, 0], "rotation": 270, "texture": "#0"}
			}
		},
		{
			"from": [0, 0, 0],
			"to": [16, 4, 16],
			"faces": {
				"north": {"uv": [0, 3, 4, 4], "texture": "#0"},
				"east": {"uv": [0, 3, 4, 4], "texture": "#0"},
				"south": {"uv": [0, 3, 4, 4], "texture": "#0"},
				"west": {"uv": [0, 3, 4, 4], "texture": "#0"},
				"up": {"uv": [4, 4, 8, 8], "texture": "#0"},
				"down": {"uv": [0, 0, 4, 4], "texture": "#0"}
			}
		},
		{
			"from": [0, 12, 0],
			"to": [16, 16, 16],
			"rotation": {"angle": 0, "axis": "y", "origin": [0, 12, 0]},
			"faces": {
				"north": {"uv": [0, 0, 4, 1], "texture": "#0"},
				"east": {"uv": [0, 0, 4, 1], "texture": "#0"},
				"south": {"uv": [0, 0, 4, 1], "texture": "#0"},
				"west": {"uv": [0, 0, 4, 1], "texture": "#0"},
				"up": {"uv": [0, 0, 4, 4], "texture": "#0"},
				"down": {"uv": [4, 4, 8, 8], "texture": "#0"}
			}
		},
		{
			"from": [12, 4, 12],
			"to": [14, 12, 14],
			"rotation": {"angle": 0, "axis": "y", "origin": [8, 8, 8]},
			"faces": {
				"east": {"uv": [0, 5.5, 0.5, 7.5], "texture": "#0"},
				"south": {"uv": [0, 5.5, 0.5, 7.5], "texture": "#0"},
				"up": {"uv": [0, 5.5, 2, 7.5], "texture": "#0"},
				"down": {"uv": [0, 5.5, 0.5, 6], "texture": "#0"}
			}
		},
		{
			"from": [2, 4, 12],
			"to": [4, 12, 14],
			"rotation": {"angle": 0, "axis": "y", "origin": [8, 8, 8]},
			"faces": {
				"south": {"uv": [0, 5.5, 0.5, 7.5], "texture": "#0"},
				"west": {"uv": [0, 5.5, 0.5, 7.5], "texture": "#0"},
				"up": {"uv": [0, 5.5, 2, 7.5], "rotation": 90, "texture": "#0"},
				"down": {"uv": [0, 5.5, 0.5, 6], "rotation": 270, "texture": "#0"}
			}
		},
		{
			"from": [2, 4, 2],
			"to": [4, 12, 4],
			"rotation": {"angle": 0, "axis": "y", "origin": [8, 8, 8]},
			"faces": {
				"north": {"uv": [0, 5.5, 0.5, 7.5], "texture": "#0"},
				"west": {"uv": [0, 5.5, 0.5, 7.5], "texture": "#0"},
				"up": {"uv": [0, 5.5, 2, 7.5], "rotation": 180, "texture": "#0"},
				"down": {"uv": [0, 5.5, 0.5, 6], "rotation": 180, "texture": "#0"}
			}
		},
		{
			"from": [12, 4, 2],
			"to": [14, 12, 4],
			"rotation": {"angle": 0, "axis": "y", "origin": [8, 8, 8]},
			"faces": {
				"north": {"uv": [0, 5.5, 0.5, 7.5], "texture": "#0"},
				"east": {"uv": [0, 5.5, 0.5, 7.5], "texture": "#0"},
				"up": {"uv": [0, 5.5, 2, 7.5], "rotation": 270, "texture": "#0"},
				"down": {"uv": [0, 5.5, 0.5, 6], "rotation": 90, "texture": "#0"}
			}
		},
		{
			"from": [4.99, 4.99, 3.99],
			"to": [11.01, 11.01, 4.01],
			"rotation": {"angle": 0, "axis": "y", "origin": [5, 5, 4]},
			"faces": {
				"north": {"uv": [0, 0, 16, 16], "texture": "#1"},
				"east": {"uv": [0, 0, 0, 6], "texture": "#1"},
				"south": {"uv": [0, 0, 6, 6], "texture": "#1"},
				"west": {"uv": [0, 0, 0, 6], "texture": "#1"},
				"up": {"uv": [0, 0, 6, 0], "texture": "#1"},
				"down": {"uv": [0, 0, 6, 0], "texture": "#1"}
			}
		},
		{
			"from": [11.99, 4.99, 4.99],
			"to": [12.01, 11.01, 11.01],
			"rotation": {"angle": 0, "axis": "x", "origin": [7, 8, 8]},
			"faces": {
				"north": {"uv": [0, 0, 0, 6], "rotation": 180, "texture": "#1"},
				"east": {"uv": [0, 0, 16, 16], "rotation": 180, "texture": "#1"},
				"south": {"uv": [0, 0, 0, 6], "rotation": 180, "texture": "#1"},
				"west": {"uv": [0, 0, 6, 6], "rotation": 180, "texture": "#1"},
				"up": {"uv": [0, 0, 6, 0], "rotation": 270, "texture": "#1"},
				"down": {"uv": [0, 0, 6, 0], "rotation": 90, "texture": "#1"}
			}
		},
		{
			"from": [4.99, 4.99, 11.99],
			"to": [11.01, 11.01, 12.01],
			"rotation": {"angle": 0, "axis": "y", "origin": [8, 8, 7]},
			"faces": {
				"north": {"uv": [0, 0, 6, 6], "texture": "#1"},
				"east": {"uv": [0, 0, 0, 6], "texture": "#1"},
				"south": {"uv": [0, 0, 16, 16], "texture": "#1"},
				"west": {"uv": [0, 0, 0, 6], "texture": "#1"},
				"up": {"uv": [0, 0, 6, 0], "rotation": 180, "texture": "#1"},
				"down": {"uv": [0, 0, 6, 0], "rotation": 180, "texture": "#1"}
			}
		},
		{
			"from": [3.99, 4.99, 4.99],
			"to": [4.01, 11.01, 11.01],
			"rotation": {"angle": 0, "axis": "x", "origin": [9, 8, 8]},
			"faces": {
				"north": {"uv": [0, 0, 0, 6], "rotation": 180, "texture": "#1"},
				"east": {"uv": [0, 0, 6, 6], "rotation": 180, "texture": "#1"},
				"south": {"uv": [0, 0, 0, 6], "rotation": 180, "texture": "#1"},
				"west": {"uv": [0, 0, 16, 16], "rotation": 180, "texture": "#1"},
				"up": {"uv": [0, 0, 6, 0], "rotation": 90, "texture": "#1"},
				"down": {"uv": [0, 0, 6, 0], "rotation": 270, "texture": "#1"}
			}
		}
	],
	"display": {},
	"groups": [
		{
			"name": "edge",
			"origin": [8, 8, 8],
			"color": 0,
			"children": [0, 1, 2, 3, 4]
		},
		{
			"name": "edge",
			"origin": [8, 8, 8],
			"color": 0,
			"children": [5, 6, 7, 8, 9]
		},
		{
			"name": "edge",
			"origin": [8, 8, 8],
			"color": 0,
			"children": [10, 11, 12, 13, 14]
		},
		{
			"name": "edge",
			"origin": [8, 8, 8],
			"color": 0,
			"children": [15, 16, 17, 18, 19]
		},
		{
			"name": "body",
			"origin": [8, 8, 8],
			"color": 0,
			"children": [20, 21, 22, 23, 24, 25]
		},
		26,
		27,
		28,
		29
	]
}